{"commands.category":"Distant-Tunnels","commands.connectCurrentWindowToTunnel.title":"Se connecter à Tunnel...","commands.getStarted.title":"Premiers pas avec les tunnels","commands.openOnDesktop.title":"Continuer à travailler dans VS Code Desktop","commands.reportIssue.title":"Signaler un problème...","commands.settings.title":"Paramètres","commands.showUsageLimits.title":"Afficher les limites d'utilisation","commands.signIntoTunnelWithDifferentAccount.title":"Se connecter à Tunnel avec un autre compte","configuration.title":"Distant – Tunnels","description":"Se connecter à une machine distante via un tunnel","settings.alwaysUpdateCLI.description":"Toujours mettre à jour le VS Code CLI si une mise à jour est disponible.","viewsWelcome.explorer.web":"Pour vous connecter à une machine sur laquelle l'accès au tunnel à distance est activé ou pour savoir comment procéder, cliquez ici :\n[Se connecter au tunnel...](command:remote-tunnels.connectCurrentWindowToTunnel)"}
